git_pull_request/__init__.py
git_pull_request/pagure.py
git_pull_request/textparse.py
git_pull_request/tests/__init__.py
git_pull_request/tests/test_gpr.py
git_pull_request/tests/test_textparse.py
git_pull_request-6.0.2.dist-info/LICENSE
git_pull_request-6.0.2.dist-info/METADATA
git_pull_request-6.0.2.dist-info/WHEEL
git_pull_request-6.0.2.dist-info/entry_points.txt
git_pull_request-6.0.2.dist-info/top_level.txt
git_pull_request-6.0.2.dist-info/RECORD
