Metadata-Version: 2.1
Name: git-pull-request
Version: 6.0.2
Summary: Command line tool to send GitHub pull requests
Home-page: https://github.com/Mergifyio/git-pull-request
Author: Julien Danjou
Author-email: jd@mergify.io
License: UNKNOWN
Platform: UNKNOWN
Classifier: Intended Audience :: Developers
Classifier: Intended Audience :: Information Technology
Classifier: License :: OSI Approved :: Apache Software License
Classifier: Operating System :: POSIX
Classifier: Programming Language :: Python
Classifier: Programming Language :: Python :: 3
Classifier: Programming Language :: Python :: 3.8
Classifier: Programming Language :: Python :: 3.9
Classifier: Programming Language :: Python :: 3.10
License-File: LICENSE
Requires-Dist: pygithub
Requires-Dist: daiquiri
Requires-Dist: attrs
Provides-Extra: test
Requires-Dist: fixtures ; extra == 'test'
